pychangcooper/__init__.py
pychangcooper/_version.py
pychangcooper/chang_cooper.py
pychangcooper/tridiagonal_solver.py
pychangcooper/io/__init__.py
pychangcooper/io/fill_plot.py
pychangcooper/photons/__init__.py
pychangcooper/photons/emission_kernel.py
pychangcooper/photons/photon_emitter.py
pychangcooper/photons/synchrotron_emission.py
pychangcooper/photons/synchrotron_kernal.py
pychangcooper/scenarios/__init__.py
pychangcooper/scenarios/continuous_powerlaw_injection.py
pychangcooper/scenarios/generic_cooling_acceleration.py
pychangcooper/scenarios/generic_cooling_component.py
pychangcooper/scenarios/synchrotron_cooling.py
pychangcooper/scenarios/synchrotron_cooling_acceleration.py
pychangcooper/utils/__init__.py
pychangcooper/utils/cmap_intervals.py
pychangcooper/utils/progress_bar.py
pychangcooper-0.5.1.dist-info/LICENSE
pychangcooper-0.5.1.dist-info/METADATA
pychangcooper-0.5.1.dist-info/WHEEL
pychangcooper-0.5.1.dist-info/top_level.txt
pychangcooper-0.5.1.dist-info/RECORD
