Metadata-Version: 2.1
Name: pychangcooper
Version: 0.5.1
Summary: A generic chang and cooper solver for fokker-planck equations
Home-page: https://github.com/grburgess/pychangcooper
Author: J. Michael Burgess
Author-email: jmichaelburgess@gmail.com
License: GPL-2+
Project-URL: Bug Tracker, https://github.com/grburgess/pychangcooper/issues
Project-URL: Source Code, https://github.com/grburgess/pychangcooper
Platform: UNKNOWN
Classifier: Development Status :: 2 - Pre-Alpha
Classifier: Environment :: Console
Classifier: Intended Audience :: Science/Research
Classifier: License :: OSI Approved :: GNU General Public License v2 or later (GPLv2+)
Classifier: Operating System :: POSIX
Classifier: Programming Language :: Python :: 3.5
Classifier: Programming Language :: Python :: 3.6
Classifier: Programming Language :: Python :: 3.7
Classifier: Programming Language :: Python :: 3.8
Classifier: Topic :: Scientific/Engineering :: Physics
Requires-Dist: numpy
Requires-Dist: scipy
Requires-Dist: ipython
Requires-Dist: matplotlib
Requires-Dist: numba
